{
  "goal_id": "g8",
  "agent_id": "a6",
  "language": "C#",
  "created_at": "2025-07-19T18:58:38Z",
  "goals": [
    {
      "id": "g8.1",
      "description": "Advanced Neural Network and Deep Learning System",
      "success_criteria": "Implement neural network architectures, training pipelines, and deep learning model management with GPU acceleration support",
      "priority": "high"
    },
    {
      "id": "g8.2",
      "description": "Advanced Computer Vision and Image Processing System", 
      "success_criteria": "Implement computer vision algorithms, image recognition, object detection, and real-time video processing capabilities",
      "priority": "high"
    },
    {
      "id": "g8.3",
      "description": "Advanced Natural Language Generation and Understanding System",
      "success_criteria": "Implement advanced NLP models, text generation, language understanding, and conversational AI capabilities",
      "priority": "high"
    }
  ],
  "dependencies": ["g1", "g2", "g3", "g4", "g5", "g6", "g7"],
  "estimated_time": "15 minutes",
  "complexity": "high"
}
