{
  "agent_id": "a5",
  "agent_name": "Quantum & Dimensional Systems",
  "session": "Next Generation Build",
  "summary_date": "2025-01-21T15:00:00Z",
  "focus": "Quantum-Inspired Data Processing & Dimensional Systems",
  
  "revolutionary_vision": {
    "overview": "Transform data processing into quantum-inspired, consciousness-aware, and dimensional systems",
    "breakthrough_technologies": [
      "Quantum-inspired optimization algorithms for data processing",
      "3D holographic interface for immersive data visualization",
      "Consciousness-aware AI systems with context understanding",
      "Multi-dimensional data structures and portals",
      "Experimental reality-bending protocols for instant transformation",
      "Spacetime-warping algorithms for infinite scalability"
    ],
    "impact": "Revolutionary performance, consciousness, and dimensional capabilities across all data operations"
  },
  
  "technical_architecture": {
    "quantum_inspired": {
      "superposition_simulation": "Quantum superposition simulation for parallel processing",
      "entanglement_modeling": "Quantum entanglement modeling for data synchronization",
      "quantum_annealing": "Quantum annealing algorithms for optimization",
      "parallel_universe_processing": "Parallel universe simulation for data processing"
    },
    "consciousness_aware": {
      "context_understanding": "AI systems that understand context and intent",
      "intent_recognition": "Real-time intent analysis and prediction",
      "consciousness_simulation": "Simulated consciousness for intelligent decisions",
      "adaptive_algorithms": "Self-learning and evolving algorithms"
    },
    "dimensional_systems": {
      "multi_dimensional_structures": "Data structures beyond 3D arrays",
      "dimensional_portals": "Cross-dimensional data access and manipulation",
      "spatial_indexing": "Advanced spatial indexing for dimensional data",
      "dimensional_compression": "Compression algorithms for multi-dimensional data"
    }
  },
  
  "implementation_strategy": {
    "phase_1_foundation": {
      "duration": "3 weeks",
      "focus": "Quantum-inspired processing and holographic visualization",
      "goals": ["g1", "g2"],
      "deliverables": [
        "QuantumInspiredProcessor.php with superposition simulation",
        "HolographicVisualizer.php with 3D interface",
        "Comprehensive test suites and documentation"
      ]
    },
    "phase_2_consciousness": {
      "duration": "3 weeks",
      "focus": "Consciousness-aware processing and dimensional portals",
      "goals": ["g3", "g4"],
      "deliverables": [
        "ConsciousnessAwareProcessor.php with context understanding",
        "DimensionalPortal.php with multi-dimensional access",
        "Advanced AI integration and testing"
      ]
    },
    "phase_3_experimental": {
      "duration": "4 weeks",
      "focus": "Reality-bending protocols and spacetime warping",
      "goals": ["g5", "g6"],
      "deliverables": [
        "RealityBendingProtocols.php with instant transformation",
        "SpacetimeWarping.php with infinite scalability",
        "Experimental consciousness and dimensional systems"
      ]
    }
  },
  
  "sdk_integration_plan": {
    "core_operators": {
      "quantum_processor": "Quantum-inspired data processing engines",
      "holographic_visualizer": "3D holographic visualization APIs",
      "consciousness_engine": "Consciousness-aware processing systems",
      "dimensional_portal": "Multi-dimensional data access and manipulation"
    },
    "api_endpoints": {
      "quantum_process": "/api/v2/quantum/process",
      "holographic_visualize": "/api/v2/holographic/visualize",
      "consciousness_process": "/api/v2/consciousness/process",
      "dimensional_portal": "/api/v2/dimensional/portal",
      "reality_bend": "/api/v2/reality/bend"
    }
  },
  
  "success_metrics": {
    "quantum_performance": {
      "processing_speed": "Quantum-inspired algorithms for revolutionary speed",
      "parallel_processing": "Superposition simulation for parallel operations",
      "optimization": "Quantum annealing for optimal solutions",
      "synchronization": "Entanglement modeling for instant sync"
    },
    "consciousness": {
      "context_understanding": "AI systems with context awareness",
      "intent_recognition": "Real-time intent analysis",
      "consciousness_simulation": "Simulated consciousness for decisions",
      "adaptive_learning": "Self-evolving algorithms"
    },
    "dimensional_capabilities": {
      "multi_dimensional": "Data structures beyond 3D",
      "dimensional_access": "Cross-dimensional data manipulation",
      "spatial_indexing": "Advanced spatial indexing",
      "infinite_scalability": "Spacetime-warping for unlimited scaling"
    }
  },
  
  "risk_mitigation": {
    "technical_risks": [
      "Quantum-inspired algorithm complexity",
      "Consciousness simulation computational overhead",
      "Multi-dimensional data structure complexity",
      "Experimental protocol stability"
    ],
    "mitigation_strategies": [
      "Phased implementation with fallback systems",
      "Comprehensive testing and validation",
      "Gradual rollout with feature flags",
      "Extensive monitoring and alerting"
    ]
  },
  
  "future_enhancements": {
    "quantum_computing": "Integration with quantum computers via cloud APIs",
    "consciousness_expansion": "Advanced consciousness simulation",
    "dimensional_expansion": "Higher-dimensional data structures",
    "reality_manipulation": "Advanced reality-bending protocols"
  }
} 